[
  {
    "id": "178414602171384fed194e24c88",
    "name": "Flap Gate",
    "site": "hostel",
    "landmarkId": "lm37",
    "category": "other",
    "points": [
      [
        26.84160550277595,
        75.56342485977832
      ],
      [
        26.841615499712095,
        75.5634605663979
      ],
      [
        26.84157178056485,
        75.56348937695303
      ],
      [
        26.841552506601513,
        75.56345266052557
      ]
    ],
    "entry": null,
    "floor": null
  },
  {
    "id": "17841471195645fb16a2b8f279",
    "name": "Subway",
    "site": "hostel",
    "landmarkId": "lm38",
    "category": "other",
    "points": [
      [
        26.841793187903203,
        75.56331086414369
      ],
      [
        26.84174875989179,
        75.56333935326165
      ],
      [
        26.84176575110602,
        75.56337817250531
      ],
      [
        26.841815558907513,
        75.56335895135395
      ]
    ],
    "entry": null,
    "floor": null
  },
  {
    "id": "17841471328735a54bbd27de898",
    "name": "To GHS (Subway)",
    "site": "hostel",
    "landmarkId": "lm41",
    "category": "other",
    "points": [
      [
        26.8418285156766,
        75.56381339332593
      ],
      [
        26.841696425215325,
        75.56386153185657
      ],
      [
        26.841746911378547,
        75.5640093738943
      ],
      [
        26.84188508766136,
        75.56396455881391
      ]
    ],
    "entry": null,
    "floor": null
  }
]